{
  "ArenaBotGroup": {
    "isXor": false,
    "columns": [
      {
        "name": "群組ID",
        "type": "uint32"
      },
      {
        "name": "角色ID",
        "type": "uint32"
      },
      {
        "name": "部隊群組ID",
        "type": "uint32"
      },
      {
        "name": "積分",
        "type": "uint32"
      },
      {
        "name": "頭像ID",
        "type": "uint32"
      },
      {
        "name": "頭像框ID",
        "type": "dstring"
      }
    ]
  },
  "arenabotteam": {
    "isXor": false,
    "columns": [
      {
        "name": "部隊群組ID",
        "type": "uint32"
      },
      {
        "name": "軍團順序",
        "type": "uint32"
      },
      {
        "name": "兵團順序",
        "type": "uint32"
      },
      {
        "name": "英雄ID",
        "type": "uint32"
      },
      {
        "name": "部隊ID",
        "type": "uint32"
      },
      {
        "name": "英雄突破次數",
        "type": "uint32"
      },
      {
        "name": "天賦點法ID",
        "type": "uint32"
      },
      {
        "name": "裝備組ID",
        "type": "uint32"
      }
    ]
  },
  "ArenaRank": {
    "isXor": false,
    "columns": [
      {
        "name": "牌位群組",
        "type": "uint16"
      },
      {
        "name": "ID",
        "type": "uint32"
      },
      {
        "name": "積分",
        "type": "uint16"
      },
      {
        "name": "最高名次",
        "type": "uint16"
      },
      {
        "name": "最低名次",
        "type": "uint16"
      },
      {
        "name": "隊伍數量",
        "type": "uint8"
      },
      {
        "name": "是否掉牌",
        "type": "uint8"
      },
      {
        "name": "積分模式",
        "type": "uint8"
      },
      {
        "name": "隊伍顯示模式",
        "type": "uint8"
      },
      {
        "name": "匹配群組",
        "type": "uint8"
      },
      {
        "name": "積分範圍",
        "type": "uint8"
      }
    ]
  },
  "ArenaSet": {
    "isXor": false,
    "columns": [
      {
        "name": "活動ID",
        "type": "uint32"
      },
      {
        "name": "入場賽季限定",
        "type": "uint8"
      },
      {
        "name": "角色等級",
        "type": "uint8"
      },
      {
        "name": "部隊數量",
        "type": "uint16"
      },
      {
        "name": "部隊技能LV",
        "type": "uint8"
      },
      {
        "name": "光陣營部隊群組ID",
        "type": "uint16"
      },
      {
        "name": "暗陣營部隊群組ID",
        "type": "uint16"
      },
      {
        "name": "技能群組ID",
        "type": "uint16"
      },
      {
        "name": "機器人群組ID",
        "type": "uint16"
      },
      {
        "name": "競技場說明",
        "type": "uint16"
      },
      {
        "name": "牌位群組",
        "type": "uint16"
      }
    ]
  },
  "ArenaSkillGroup": {
    "isXor": false,
    "columns": [
      {
        "name": "ID",
        "type": "uint16"
      },
      {
        "name": "技能類型",
        "type": "uint8"
      },
      {
        "name": "技能ID",
        "type": "uint16"
      },
      {
        "name": "技能等級",
        "type": "uint8"
      }
    ]
  },
  "ArenaSoldierGroup": {
    "isXor": false,
    "columns": [
      {
        "name": "部隊群組ID",
        "type": "uint16"
      },
      {
        "name": "部隊ID",
        "type": "uint16"
      },
      {
        "name": "限制群組",
        "type": "uint16"
      },
      {
        "name": "限制群組Cost",
        "type": "uint16"
      }
    ]
  },
  "arenasoldierlimitgroup": {
    "isXor": false,
    "columns": [
      {
        "name": "限制群組",
        "type": "uint16"
      },
      {
        "name": "群組圖示",
        "type": "uint16"
      },
      {
        "name": "Cost上限",
        "type": "uint16"
      }
    ]
  },
  "ArenaTimes": {
    "isXor": false,
    "columns": [
      {
        "name": "次數",
        "type": "uint8"
      },
      {
        "name": "所需鑽石",
        "type": "uint16"
      }
    ]
  }
}